web/dispatch/core/__init__.py
web/dispatch/core/crumb.py
web/dispatch/core/release.py
web/dispatch/core/util.py
web/dispatch/core/__pycache__/__init__.cpython-36.opt-1.pyc
web/dispatch/core/__pycache__/crumb.cpython-36.opt-1.pyc
web/dispatch/core/__pycache__/release.cpython-36.opt-1.pyc
web/dispatch/core/__pycache__/util.cpython-36.opt-1.pyc
web.dispatch-3.0.1.dist-info/DESCRIPTION.rst
web.dispatch-3.0.1.dist-info/METADATA
web.dispatch-3.0.1.dist-info/RECORD
web.dispatch-3.0.1.dist-info/WHEEL
web.dispatch-3.0.1.dist-info/entry_points.txt
web.dispatch-3.0.1.dist-info/metadata.json
web.dispatch-3.0.1.dist-info/top_level.txt
