Metadata-Version: 2.0
Name: web.dispatch
Version: 3.0.1
Summary: Dispatch; a method to resolve path components to Python objects and enumerate available children using pluggable search mechanisms.
Home-page: https://github.com/marrow/web.dispatch
Author: Alice Bevan-McGregor
Author-email: alice@gothcandy.com
License: MIT
Download-URL: https://pypi.org/project/web.dispatch/
Keywords: marrow,dispatch,url dispatch,endpoint discovery
Platform: UNKNOWN
Classifier: Development Status :: 5 - Production/Stable
Classifier: Environment :: Console
Classifier: Environment :: Web Environment
Classifier: Intended Audience :: Developers
Classifier: License :: OSI Approved :: MIT License
Classifier: Operating System :: OS Independent
Classifier: Programming Language :: Python
Classifier: Programming Language :: Python :: 3
Classifier: Programming Language :: Python :: 3.3
Classifier: Programming Language :: Python :: 3.4
Classifier: Programming Language :: Python :: 3.5
Classifier: Programming Language :: Python :: 3.6
Classifier: Programming Language :: Python :: Implementation :: CPython
Classifier: Programming Language :: Python :: Implementation :: PyPy
Classifier: Topic :: Software Development :: Libraries :: Python Modules
Requires-Dist: pathlib
Provides-Extra: development
Requires-Dist: pre-commit; extra == 'development'
Requires-Dist: pytest; extra == 'development'
Requires-Dist: pytest-catchlog; extra == 'development'
Requires-Dist: pytest-cov; extra == 'development'
Requires-Dist: pytest-flakes; extra == 'development'
Requires-Dist: pytest-isort; extra == 'development'
